resume_markdown/__init__.py
resume_markdown/__main__.py
resume_markdown/resume.css
resume_markdown/resume.md
resume_markdown-1.0.1.dist-info/METADATA
resume_markdown-1.0.1.dist-info/WHEEL
resume_markdown-1.0.1.dist-info/entry_points.txt
resume_markdown-1.0.1.dist-info/licenses/LICENSE
resume_markdown-1.0.1.dist-info/RECORD
