Metadata-Version: 2.4
Name: resume-markdown
Version: 1.0.1
Summary: Convert Markdown resumes to HTML and PDF
Project-URL: Homepage, https://github.com/mikepqr/resume-markdown
Project-URL: Repository, https://github.com/mikepqr/resume-markdown
Project-URL: Issues, https://github.com/mikepqr/resume-markdown/issues
Author-email: Mike Lee Williams <mike@mike.place>
License: MIT
License-File: LICENSE
Classifier: Development Status :: 5 - Production/Stable
Classifier: Intended Audience :: End Users/Desktop
Classifier: License :: OSI Approved :: MIT License
Classifier: Programming Language :: Python :: 3
Classifier: Programming Language :: Python :: 3.9
Classifier: Programming Language :: Python :: 3.10
Classifier: Programming Language :: Python :: 3.11
Classifier: Programming Language :: Python :: 3.12
Classifier: Topic :: Text Processing :: Markup :: Markdown
Requires-Python: >=3.9
Requires-Dist: markdown>=3.0
